<?xml version="1.0" encoding="utf-8"?>
<world name="World 10" map="g1_World10" width="21" height="15">
    <players number="4" />
    <items>
      <item type="Soldier" level="1" x="2" y="2" />
      <item type="Soldier" level="1" x="6" y="2" />
      <item type="Soldier" level="1" x="2" y="4" />
      <item type="Soldier" level="1" x="6" y="4" />
      <item type="Soldier" level="1" x="14" y="2" />
      <item type="Soldier" level="1" x="18" y="2" />
      <item type="Soldier" level="1" x="14" y="4" />
      <item type="Soldier" level="1" x="18" y="4" />
      <item type="Soldier" level="1" x="2" y="10" />
      <item type="Soldier" level="1" x="6" y="10" />
      <item type="Soldier" level="1" x="2" y="12" />
      <item type="Soldier" level="1" x="6" y="12" />
      <item type="Soldier" level="1" x="14" y="10" />
      <item type="Soldier" level="1" x="18" y="10" />
      <item type="Soldier" level="1" x="14" y="12" />
      <item type="Soldier" level="1" x="18" y="12" />



      <item type="Capital" golds="45" x="4" y="3" />
      <item type="Capital" golds="45" x="16" y="3" />
      <item type="Capital" golds="45" x="4" y="11" />
      <item type="Capital" golds="45" x="16" y="11" />

      <item type="Tree" x="5" y="12" />
      <item type="Tree" x="13" y="11" />
      <item type="Tree" x="6" y="7" />
      <item type="Tree" x="6" y="11" />
      <item type="Tree" x="9" y="1" />
      <item type="Tree" x="13" y="6" />
      <item type="Tree" x="8" y="11" />
      <item type="Tree" x="6" y="1" />
    </items>

</world>
